{
    "Result" : {
        "ID" : "one chunk 2018-11-09 17:38:18",
        "status" : "final",
        "computation" : {
            "startTime" : "2018-11-09 17:38:18",
            "duration" : "77ms",
            "finishTime" : "2018-11-09 17:38:18",
            "CC_versionLong" : "[ViP CCv4.6.1 (C chain)v1.4 (Matlab chain)v2.9 (Octave chain)v2.0 (DuMuX chain)v1.3 (C++ chain)v1.9 (Java chain)v1.8 (Wed Oct  3 12:52:35 CEST 2018)]",
            "CC_version" : "ViP CCv4.6.1",
            "chain_version" : "(C chain)v1.4",
            "technicalInfo" : {
                "host" : "nfldevvip12",
                "PID" : "41277",
                "ID" : "#233"
            },
            "userInfo" : {
                "summary" : "(C chain)v1.4 failed.",
                "elements" : [
                    {
                        "severity" : "error",
                        "type" : "callcheck",
                        "message" : "[C function filtering] Checking failed (original source: S, line (corrected): 1, col: 1): invalid preprozessor line: #def\\",
                        "source" : {
                            "elementID" : "S",
                            "extract" : "#def\\",
                            "begin" : 0,
                            "end" : 5,
                            "line" : 1,
                            "col" : 1
                        }
                    }
                ]
            }
        },
        "Solution" : {
            "postTime" : "2011-05-09 17:29:02+02:00",
            "ID" : "127.32.15.3#127",
            "comment" : "solution without modified elements",
            "exercise" : "https://nfldevvipecs.rus.uni-stuttgart.de/numlab/exercises/36490",
            "exerciseModifications" : {
                "elements" : [
                ]
            }
        },
        "elements" : [
        ]
    }
}